hatch_calvar_sample/__about__.py
hatch_calvar_sample/__init__.py
hatch_calvar_sample/cli.py
hatch_calvar_sample-2026.1.19.2.dist-info/METADATA
hatch_calvar_sample-2026.1.19.2.dist-info/WHEEL
hatch_calvar_sample-2026.1.19.2.dist-info/entry_points.txt
hatch_calvar_sample-2026.1.19.2.dist-info/licenses/LICENSE.txt
hatch_calvar_sample-2026.1.19.2.dist-info/RECORD
