Metadata-Version: 2.4
Name: hatch-calvar-sample
Version: 2026.1.19.2
Summary: Sample project demonstrating CalVer (YYYY.MM.DD.MICRO) with hatch
Project-URL: Documentation, https://github.com/QAToolist/hatch-calvar-sample#readme
Project-URL: Issues, https://github.com/QAToolist/hatch-calvar-sample/issues
Project-URL: Source, https://github.com/QAToolist/hatch-calvar-sample
Author-email: QAToolist <qatoolist@gmail.com>
License-Expression: MIT
License-File: LICENSE.txt
Classifier: Development Status :: 4 - Beta
Classifier: Programming Language :: Python
Classifier: Programming Language :: Python :: 3.8
Classifier: Programming Language :: Python :: 3.9
Classifier: Programming Language :: Python :: 3.10
Classifier: Programming Language :: Python :: 3.11
Classifier: Programming Language :: Python :: 3.12
Classifier: Programming Language :: Python :: Implementation :: CPython
Classifier: Programming Language :: Python :: Implementation :: PyPy
Requires-Python: >=3.8
Provides-Extra: dev
Requires-Dist: bandit[sarif]>=1.7.0; extra == 'dev'
Requires-Dist: black>=24.1.0; extra == 'dev'
Requires-Dist: interrogate>=1.5.0; extra == 'dev'
Requires-Dist: isort>=5.13.0; extra == 'dev'
Requires-Dist: mypy>=1.0.0; extra == 'dev'
Requires-Dist: pip-audit>=2.6.0; extra == 'dev'
Requires-Dist: pip-licenses>=4.0.0; extra == 'dev'
Requires-Dist: pre-commit>=3.0.0; extra == 'dev'
Requires-Dist: pydocstyle>=6.3.0; extra == 'dev'
Requires-Dist: pytest-cov>=4.0.0; extra == 'dev'
Requires-Dist: pytest>=7.0.0; extra == 'dev'
Requires-Dist: radon>=6.0.0; extra == 'dev'
Requires-Dist: ruff>=0.1.0; extra == 'dev'
Requires-Dist: safety>=2.3.0; extra == 'dev'
Requires-Dist: xenon>=0.9.0; extra == 'dev'
Provides-Extra: docs
Requires-Dist: interrogate>=1.5.0; extra == 'docs'
Requires-Dist: pydocstyle>=6.3.0; extra == 'docs'
Provides-Extra: lint
Requires-Dist: bandit>=1.7.0; extra == 'lint'
Requires-Dist: black>=24.1.0; extra == 'lint'
Requires-Dist: isort>=5.13.0; extra == 'lint'
Requires-Dist: mypy>=1.0.0; extra == 'lint'
Requires-Dist: pre-commit>=3.0.0; extra == 'lint'
Requires-Dist: ruff>=0.1.0; extra == 'lint'
Provides-Extra: quality
Requires-Dist: radon>=6.0.0; extra == 'quality'
Requires-Dist: xenon>=0.9.0; extra == 'quality'
Provides-Extra: security
Requires-Dist: bandit[sarif]>=1.7.0; extra == 'security'
Requires-Dist: pip-audit>=2.6.0; extra == 'security'
Requires-Dist: safety>=2.3.0; extra == 'security'
Provides-Extra: test
Requires-Dist: pytest-cov>=4.0.0; extra == 'test'
Requires-Dist: pytest>=7.0.0; extra == 'test'
